mopeka_iot_ble/__init__.py
mopeka_iot_ble/parser.py
mopeka_iot_ble/py.typed
mopeka_iot_ble-0.7.0.dist-info/LICENSE
mopeka_iot_ble-0.7.0.dist-info/METADATA
mopeka_iot_ble-0.7.0.dist-info/WHEEL
mopeka_iot_ble-0.7.0.dist-info/RECORD
